gatun/__init__.py
gatun/arena.py
gatun/async_client.py
gatun/bridge.py
gatun/bridge_adapters.py
gatun/client.py
gatun/config.py
gatun/launcher.py
gatun/py.typed
gatun/generated/org/__init__.py
gatun/generated/org/gatun/__init__.py
gatun/generated/org/gatun/protocol/Action.py
gatun/generated/org/gatun/protocol/Argument.py
gatun/generated/org/gatun/protocol/ArrayVal.py
gatun/generated/org/gatun/protocol/ArrowBatchDescriptor.py
gatun/generated/org/gatun/protocol/BatchCommand.py
gatun/generated/org/gatun/protocol/BatchResponse.py
gatun/generated/org/gatun/protocol/BoolVal.py
gatun/generated/org/gatun/protocol/BufferDescriptor.py
gatun/generated/org/gatun/protocol/CallbackRef.py
gatun/generated/org/gatun/protocol/CallbackResult.py
gatun/generated/org/gatun/protocol/CharVal.py
gatun/generated/org/gatun/protocol/Command.py
gatun/generated/org/gatun/protocol/CreateObjectsRequest.py
gatun/generated/org/gatun/protocol/DoubleVal.py
gatun/generated/org/gatun/protocol/ElementType.py
gatun/generated/org/gatun/protocol/FieldNode.py
gatun/generated/org/gatun/protocol/GetFieldsRequest.py
gatun/generated/org/gatun/protocol/IntVal.py
gatun/generated/org/gatun/protocol/InvokeMethodsRequest.py
gatun/generated/org/gatun/protocol/ListVal.py
gatun/generated/org/gatun/protocol/MapEntry.py
gatun/generated/org/gatun/protocol/MapVal.py
gatun/generated/org/gatun/protocol/MethodCall.py
gatun/generated/org/gatun/protocol/NullVal.py
gatun/generated/org/gatun/protocol/ObjectRef.py
gatun/generated/org/gatun/protocol/ObjectSpec.py
gatun/generated/org/gatun/protocol/Response.py
gatun/generated/org/gatun/protocol/StringVal.py
gatun/generated/org/gatun/protocol/Value.py
gatun/generated/org/gatun/protocol/__init__.py
gatun/jars/gatun-server-all.jar
gatun-0.2.1.dist-info/licenses/LICENSE
gatun-0.2.1.dist-info/METADATA
gatun-0.2.1.dist-info/WHEEL
gatun-0.2.1.dist-info/top_level.txt
gatun-0.2.1.dist-info/RECORD
