Metadata-Version: 2.4
Name: gatun
Version: 0.2.1
Summary: High-performance Python-to-Java bridge using shared memory and Apache Arrow
Author-email: Fangchen Li <fangchen.li@outlook.com>
License-Expression: Apache-2.0
Project-URL: Homepage, https://github.com/forge-labs-dev/gatun
Project-URL: Repository, https://github.com/forge-labs-dev/gatun
Project-URL: Issues, https://github.com/forge-labs-dev/gatun/issues
Keywords: java,jvm,bridge,ipc,shared-memory,arrow,pyspark,interop,rpc,flatbuffers
Classifier: Development Status :: 3 - Alpha
Classifier: Programming Language :: Python :: 3.13
Classifier: Programming Language :: Python :: 3.14
Classifier: Programming Language :: Java
Classifier: Topic :: Software Development :: Libraries :: Python Modules
Classifier: Topic :: System :: Distributed Computing
Classifier: Intended Audience :: Developers
Classifier: Operating System :: POSIX
Classifier: Operating System :: MacOS
Requires-Python: >=3.13
License-File: LICENSE
Requires-Dist: flatbuffers>=23.5.26
Requires-Dist: pyarrow>=22.0.0
Dynamic: license-file
